{
  "course_name": "Data Management",
  "course_description": "The MIT Libraries Data Management Group hosts a set of workshops during IAP  and throughout the year to assist MIT faculty and researchers with data set control, maintenance, and sharing. This resource contains a selection of presentations from those workshops. Topics include an introduction to data management, details on data sharing and storage, data management using the DMPTool, file organization, version control, and an overview of the open data requirements of various funding sources.",
  "topics": [
    "Business",
    "Information Technology",
    "Project Management",
    "Business",
    "Information Technology",
    "Project Management"
  ],
  "syllabus_content": "",
  "files": []
}